README.md
setup.py
n2/__init__.py
n2/log.py
n2/cache/__init__.py
n2/cache/cache.py
n2/core/__init__.py
n2/core/cutout.py
n2/core/masking.py
n2/core/physical_properties.py
n2/core/regrid.py
n2/core/smoothing.py
n2/core/velocity.py
n2/data/__init__.py
n2/data/fitsimage.py
n2/jupyter_tools/__init__.py
n2/jupyter_tools/jpy_red_blue_cube.py
n2/jupyter_tools/jpy_red_blue_image.py
n2/jupyter_tools/jpy_rgbimage.py
n2/plot/__init__.py
n2/plot/axes.py
n2/plot/rcparams.py
n2_tools.egg-info/PKG-INFO
n2_tools.egg-info/SOURCES.txt
n2_tools.egg-info/dependency_links.txt
n2_tools.egg-info/top_level.txt