Metadata-Version: 1.1
Name: n2-tools
Version: 0.0.25
Summary: tools for astronomy data
Home-page: https://github.com/nanten2/n2-tools
Author: Atsushi Nishimura
Author-email: ars096@gmail.com
License: MIT
Platform: UNKNOWN
Classifier: Programming Language :: Python :: 3
Classifier: License :: OSI Approved :: MIT License
